_examples/__init__.py
bibtex_gen/__init__.py
bibtex_gen/main.py
bibtex_gen/mendeley.py
examples/__init__.py
tests/__init__.py
tests/test_doi.py
bibtex_gen-0.2.0.dist-info/LICENSE.md
bibtex_gen-0.2.0.dist-info/METADATA
bibtex_gen-0.2.0.dist-info/WHEEL
bibtex_gen-0.2.0.dist-info/entry_points.txt
bibtex_gen-0.2.0.dist-info/top_level.txt
bibtex_gen-0.2.0.dist-info/RECORD
