Metadata-Version: 2.1
Name: bibtex-gen
Version: 0.2.0
Summary: Generate BibTeX reference objects from DOIs and strings
Home-page: https://github.com/nickderobertis/bibtex-gen
Author: Nick DeRobertis
Author-email: whoopnip@gmail.com
License: MIT
Project-URL: Code, https://github.com/nickderobertis/bibtex-gen
Project-URL: Documentation, https://nickderobertis.github.io/bibtex-gen
Platform: UNKNOWN
Classifier: Development Status :: 3 - Alpha
Classifier: Intended Audience :: Developers
Classifier: Programming Language :: Python :: 3.6
Classifier: Programming Language :: Python :: 3.7
Requires-Dist: mendeley2
Requires-Dist: pyexlatex
